NikChat/__init__.py
NikChat/results.py
NikChat/training.py
NikChat-2.3.3.2.dist-info/LICENSE
NikChat-2.3.3.2.dist-info/METADATA
NikChat-2.3.3.2.dist-info/WHEEL
NikChat-2.3.3.2.dist-info/top_level.txt
NikChat-2.3.3.2.dist-info/RECORD
