Metadata-Version: 2.1
Name: NikChat
Version: 2.3.3.2
Summary: A full-fledged chatbot designed to be incorperated into other projects. (Speeds of 0.1 seconds)
Home-page: https://github.com/Nikhilodeon1/NikChat
Author: Nikhil Tamvada (Nikhilodeon1)
Author-email: nikhiltamvada@gmail.com
Classifier: Programming Language :: Python :: 3
Classifier: License :: OSI Approved :: MIT License
Classifier: Operating System :: OS Independent
Requires-Python: >=3.6
License-File: LICENSE
